pyiwara/__init__.py
pyiwara/modules.py
pyiwara-1.0.0.dist-info/METADATA
pyiwara-1.0.0.dist-info/WHEEL
pyiwara-1.0.0.dist-info/top_level.txt
pyiwara-1.0.0.dist-info/RECORD
